ai_scrm/__init__.py
ai_scrm/abom/__init__.py
ai_scrm/abom/builder.py
ai_scrm/abom/exceptions.py
ai_scrm/abom/models.py
ai_scrm/cli/__init__.py
ai_scrm/integrations/__init__.py
ai_scrm/integrations/integrations.py
ai_scrm/monitor/__init__.py
ai_scrm/monitor/monitor.py
ai_scrm/scanner/__init__.py
ai_scrm/scanner/exceptions.py
ai_scrm/scanner/inference.py
ai_scrm/scanner/mcp_discovery.py
ai_scrm/scanner/metadata.py
ai_scrm/scanner/scanner.py
ai_scrm/schemas/abom.schema.json
ai_scrm/trust/__init__.py
ai_scrm/trust/assertion.py
ai_scrm/trust/exceptions.py
ai_scrm/trust/signing.py
ai_scrm/trust/verification.py
ai_scrm/validation/__init__.py
ai_scrm/validation/detector.py
ai_scrm/validation/emitter.py
ai_scrm/validation/events.py
ai_scrm/validation/exceptions.py
ai_scrm-1.0.1.dist-info/licenses/LICENSE
ai_scrm-1.0.1.dist-info/METADATA
ai_scrm-1.0.1.dist-info/WHEEL
ai_scrm-1.0.1.dist-info/entry_points.txt
ai_scrm-1.0.1.dist-info/top_level.txt
ai_scrm-1.0.1.dist-info/RECORD
