Metadata-Version: 2.4
Name: ai-scrm
Version: 1.0.1
Summary: AI Supply Chain Risk Management - Auto-discovery, signing, and continuous validation for AI systems
Author: Shawn Kahalewai Reilly
Maintainer: Shawn Kahalewai Reilly
License: Apache-2.0
Project-URL: Homepage, https://github.com/kahalewai/ai-scrm
Project-URL: Documentation, https://github.com/kahalewai/ai-scrm/python
Project-URL: Repository, https://github.com/kahalewai/ai-scrm
Project-URL: Issues, https://github.com/kahalewai/ai-scrm/issues
Keywords: ai,security,supply-chain,sbom,abom,cyclonedx,machine-learning,llm,provenance,integrity,ai-scs
Classifier: Development Status :: 3 - Alpha
Classifier: Intended Audience :: Developers
Classifier: Intended Audience :: Information Technology
Classifier: License :: OSI Approved :: Apache Software License
Classifier: Operating System :: OS Independent
Classifier: Programming Language :: Python :: 3
Classifier: Programming Language :: Python :: 3.9
Classifier: Programming Language :: Python :: 3.10
Classifier: Programming Language :: Python :: 3.11
Classifier: Programming Language :: Python :: 3.12
Classifier: Topic :: Security
Classifier: Topic :: Software Development :: Libraries :: Python Modules
Requires-Python: >=3.9
License-File: LICENSE
Requires-Dist: click>=8.0.0
Requires-Dist: rich>=13.0.0
Provides-Extra: crypto
Requires-Dist: cryptography>=41.0.0; extra == "crypto"
Provides-Extra: schema
Requires-Dist: jsonschema>=4.0.0; extra == "schema"
Provides-Extra: yaml
Requires-Dist: pyyaml>=6.0; extra == "yaml"
Provides-Extra: all
Requires-Dist: cryptography>=41.0.0; extra == "all"
Requires-Dist: jsonschema>=4.0.0; extra == "all"
Requires-Dist: pyyaml>=6.0; extra == "all"
Provides-Extra: dev
Requires-Dist: pytest>=7.0.0; extra == "dev"
Requires-Dist: pytest-cov>=4.0.0; extra == "dev"
Requires-Dist: black>=23.0.0; extra == "dev"
Requires-Dist: mypy>=1.0.0; extra == "dev"
Requires-Dist: ruff>=0.1.0; extra == "dev"
Dynamic: license-file
